README.rst
setup.py
omx/__init__.py
omx/core.py
omx/decl.py
omx/dump.py
omx/load.py
omx/target.py
omx/template.py
omx.egg-info/PKG-INFO
omx.egg-info/SOURCES.txt
omx.egg-info/dependency_links.txt
omx.egg-info/requires.txt
omx.egg-info/top_level.txt