Metadata-Version: 1.0
Name: omx
Version: 0.1.0
Summary: Declarative XML parsing and serialization
Home-page: UNKNOWN
Author: David Keijser
Author-email: keijser@gmail.com
License: MIT
Keywords: xml lxml etree declarative
Platform: UNKNOWN
